memunit/__init__.py
memunit-0.5.2.dist-info/LICENSE
memunit-0.5.2.dist-info/METADATA
memunit-0.5.2.dist-info/WHEEL
memunit-0.5.2.dist-info/top_level.txt
memunit-0.5.2.dist-info/RECORD
